ultralyticsplus/__init__.py
ultralyticsplus/cli.py
ultralyticsplus/hf_utils.py
ultralyticsplus/other_utils.py
ultralyticsplus/roboflow_utils.py
ultralyticsplus/ultralytics_utils.py
ultralyticsplus-0.1.0.dist-info/LICENSE
ultralyticsplus-0.1.0.dist-info/METADATA
ultralyticsplus-0.1.0.dist-info/WHEEL
ultralyticsplus-0.1.0.dist-info/entry_points.txt
ultralyticsplus-0.1.0.dist-info/top_level.txt
ultralyticsplus-0.1.0.dist-info/RECORD
